playtrak_sentinel-0.1.0.dist-info/licenses/LICENSE
sentinel_simplecli/__init__.py
sentinel_simplecli/cli.py
playtrak_sentinel-0.1.0.dist-info/METADATA
playtrak_sentinel-0.1.0.dist-info/WHEEL
playtrak_sentinel-0.1.0.dist-info/entry_points.txt
playtrak_sentinel-0.1.0.dist-info/top_level.txt
playtrak_sentinel-0.1.0.dist-info/RECORD
